qstn/__init__.py
qstn/prompt_builder.py
qstn/survey_manager.py
qstn/inference/__init__.py
qstn/inference/dynamic_pydantic.py
qstn/inference/local_inference.py
qstn/inference/reasoning_parser.py
qstn/inference/remote_inference.py
qstn/inference/response_generation.py
qstn/inference/survey_inference.py
qstn/parser/__init__.py
qstn/parser/llm_answer_parser.py
qstn/utilities/__init__.py
qstn/utilities/constants.py
qstn/utilities/placeholder.py
qstn/utilities/prompt_creation.py
qstn/utilities/prompt_perturbations.py
qstn/utilities/prompt_templates.py
qstn/utilities/survey_objects.py
qstn/utilities/utils.py
qstn-0.1.5.dist-info/METADATA
qstn-0.1.5.dist-info/WHEEL
qstn-0.1.5.dist-info/licenses/LICENSE
qstn-0.1.5.dist-info/RECORD
