Metadata-Version: 2.4
Name: qstn
Version: 0.1.5
Summary: A Modular Framework for Robust Questionnaire Inference with Large Language Models
Project-URL: Homepage, https://github.com/dess-mannheim/QSTN
Project-URL: Documentation, https://qstn.readthedocs.io/en/latest/index.html
Author-email: Maximilian Kreutner <maximilian.kreutner@uni-mannheim.de>
License-Expression: MIT
License-File: LICENSE
Classifier: Operating System :: OS Independent
Classifier: Programming Language :: Python :: 3
Requires-Python: >=3.12
Requires-Dist: json-repair
Requires-Dist: openai
Requires-Dist: pandas>=2.2.3
Requires-Dist: pydantic>=2.11.4
Requires-Dist: vllm>=0.12
